<?xml version="1.0" encoding="utf-8" ?>
<dwsync>
<file name="bfgrill rendering.jpg" server="ftp.ryanwdd.com" local="129874791443115833" remote="129882572400000000" Dst="-1" />
<file name="bf_grill_cs.jpg" server="ftp.ryanwdd.com" local="129874794429986672" remote="129882572400000000" Dst="-1" />
<file name="bfgrill rendering.jpg" server="ftp.ryanwdd.com/dogwoodlandscapes/" local="129874791443115833" remote="129882582000000000" Dst="-1" />
<file name="bf_grill_cs.jpg" server="ftp.ryanwdd.com/dogwoodlandscapes/" local="129874794429986672" remote="129882582000000000" Dst="-1" />
<file name="bf_grill_cs.jpg" server="www.2020mediadesign.com" local="129874794429986672" remote="130045626600000000" Dst="1" />
<file name="bfgrill rendering.jpg" server="www.2020mediadesign.com" local="129874791443115833" remote="130045626600000000" Dst="1" />
<file name="bf_grill_cs.jpg" server="www.2020mediadesign.com/2020/" local="129874794429986672" remote="129954048600000000" Dst="2" />
<file name="bfgrill rendering.jpg" server="www.2020mediadesign.com/2020/" local="129874791443115833" remote="129954048600000000" Dst="2" />
</dwsync>